cubicweb_varnish/__init__.py
cubicweb_varnish/__pkginfo__.py
cubicweb_varnish/entities.py
cubicweb_varnish/hooks.py
cubicweb_varnish/site_cubicweb.py
cubicweb_varnish/varnishadm.py
cubicweb_varnish/views.py
cubicweb_varnish/i18n/en.po
cubicweb_varnish/i18n/es.po
cubicweb_varnish/i18n/fr.po
cubicweb_varnish/migration/postcreate.py
cubicweb_varnish-1.0.0.dist-info/METADATA
cubicweb_varnish-1.0.0.dist-info/WHEEL
cubicweb_varnish-1.0.0.dist-info/entry_points.txt
cubicweb_varnish-1.0.0.dist-info/top_level.txt
cubicweb_varnish-1.0.0.dist-info/RECORD
