Metadata-Version: 2.1
Name: cubicweb-varnish
Version: 1.0.0
Summary: cubicweb varnish helper
Home-page: https://forge.extranet.logilab.fr/cubicweb/cubes/cubicweb-varnish
Author: LOGILAB S.A. (Paris, FRANCE)
Author-email: contact@logilab.fr
License: LGPL-2.1
Classifier: Environment :: Web Environment
Classifier: Framework :: CubicWeb
Classifier: Programming Language :: Python :: 3
Classifier: Programming Language :: JavaScript
Requires-Dist: cubicweb (<5.0.0,>=3.31.0)
